froglabs/__init__.py
froglabs/cli.py
froglabs/clients.py
froglabs/exceptions.py
froglabs/utils.py
froglabs-0.2.0.dist-info/LICENSE.txt
froglabs-0.2.0.dist-info/METADATA
froglabs-0.2.0.dist-info/WHEEL
froglabs-0.2.0.dist-info/entry_points.txt
froglabs-0.2.0.dist-info/top_level.txt
froglabs-0.2.0.dist-info/zip-safe
froglabs-0.2.0.dist-info/RECORD
