Metadata-Version: 2.1
Name: froglabs
Version: 0.2.0
Summary: Froglabs Toolkit
Home-page: UNKNOWN
Author: Froglabs, Inc
Author-email: team@froglabs.ai
License: UNKNOWN
Platform: UNKNOWN
Requires-Dist: click
Requires-Dist: dask
Requires-Dist: netcdf4
Requires-Dist: numpy (>=1.12)
Requires-Dist: pandas (>=0.19.2)
Requires-Dist: requests
Requires-Dist: six
Requires-Dist: toolz
Requires-Dist: tqdm
Requires-Dist: xarray (>=0.12.3)
